<?xml version="1.0" encoding="UTF-8" ?>

<tree xmlns:xsi="http://www.w3.org/2001/XMLSchema-instance"
      xsi:noNamespaceSchemaLocation="../../TCP.xsd">
<node xsi:type="constructor" type="XORC">
<left xsi:type="constructor" type="XORD">
<left xsi:type="basicService" identifier="40">
<quadruple>
<d1>11</d1>
<c1>390</c1>
<d2>110</d2>
<c2>108</c2>
</quadruple>
<quadruple>
<d1>110</d1>
<c1>359</c1>
<d2>125</d2>
<c2>246</c2>
</quadruple>
<quadruple>
<d1>125</d1>
<c1>506</c1>
<d2>191</d2>
<c2>564</c2>
</quadruple>
<quadruple>
<d1>191</d1>
<c1>178</c1>
<d2>268</d2>
<c2>483</c2>
</quadruple>
<quadruple>
<d1>268</d1>
<c1>549</c1>
<d2>560</d2>
<c2>186</c2>
</quadruple>
</left>
<right xsi:type="basicService" identifier="41">
<quadruple>
<d1>11</d1>
<c1>448</c1>
<d2>90</d2>
<c2>400</c2>
</quadruple>
<quadruple>
<d1>90</d1>
<c1>466</c1>
<d2>106</d2>
<c2>553</c2>
</quadruple>
<quadruple>
<d1>106</d1>
<c1>120</c1>
<d2>125</d2>
<c2>528</c2>
</quadruple>
<quadruple>
<d1>125</d1>
<c1>565</c1>
<d2>230</d2>
<c2>487</c2>
</quadruple>
<quadruple>
<d1>230</d1>
<c1>233</c1>
<d2>560</d2>
<c2>338</c2>
</quadruple>
</right>
</left>
<right xsi:type="basicService" identifier="42">
<quadruple>
<d1>11</d1>
<c1>307</c1>
<d2>100</d2>
<c2>188</c2>
</quadruple>
<quadruple>
<d1>100</d1>
<c1>497</c1>
<d2>133</d2>
<c2>403</c2>
</quadruple>
<quadruple>
<d1>133</d1>
<c1>190</c1>
<d2>219</d2>
<c2>44</c2>
</quadruple>
<quadruple>
<d1>219</d1>
<c1>201</c1>
<d2>301</d2>
<c2>526</c2>
</quadruple>
<quadruple>
<d1>301</d1>
<c1>338</c1>
<d2>560</d2>
<c2>505</c2>
</quadruple>
</right>
</node>
</tree>