<?xml version="1.0" encoding="UTF-8" ?>

<tree xmlns:xsi="http://www.w3.org/2001/XMLSchema-instance"
      xsi:noNamespaceSchemaLocation="../../TCP.xsd">
<node xsi:type="constructor" type="XORC">
<left xsi:type="basicService" identifier="139">
<quadruple>
<d1>6</d1>
<c1>1115</c1>
<d2>19</d2>
<c2>1310</c2>
</quadruple>
<quadruple>
<d1>19</d1>
<c1>1047</c1>
<d2>40</d2>
<c2>2551</c2>
</quadruple>
<quadruple>
<d1>40</d1>
<c1>2132</c1>
<d2>70</d2>
<c2>1297</c2>
</quadruple>
<quadruple>
<d1>70</d1>
<c1>866</c1>
<d2>92</d2>
<c2>2955</c2>
</quadruple>
<quadruple>
<d1>92</d1>
<c1>1793</c1>
<d2>118</d2>
<c2>943</c2>
</quadruple>
<quadruple>
<d1>118</d1>
<c1>1349</c1>
<d2>148</d2>
<c2>1364</c2>
</quadruple>
<quadruple>
<d1>148</d1>
<c1>607</c1>
<d2>179</d2>
<c2>39</c2>
</quadruple>
<quadruple>
<d1>179</d1>
<c1>2328</c1>
<d2>211</d2>
<c2>1210</c2>
</quadruple>
<quadruple>
<d1>211</d1>
<c1>1368</c1>
<d2>254</d2>
<c2>696</c2>
</quadruple>
<quadruple>
<d1>254</d1>
<c1>411</c1>
<d2>310</d2>
<c2>2477</c2>
</quadruple>
<quadruple>
<d1>310</d1>
<c1>2759</c1>
<d2>361</d2>
<c2>1635</c2>
</quadruple>
<quadruple>
<d1>361</d1>
<c1>787</c1>
<d2>368</d2>
<c2>2357</c2>
</quadruple>
<quadruple>
<d1>368</d1>
<c1>2849</c1>
<d2>384</d2>
<c2>2560</c2>
</quadruple>
<quadruple>
<d1>384</d1>
<c1>911</c1>
<d2>399</d2>
<c2>2128</c2>
</quadruple>
<quadruple>
<d1>399</d1>
<c1>1611</c1>
<d2>457</d2>
<c2>2465</c2>
</quadruple>
<quadruple>
<d1>457</d1>
<c1>898</c1>
<d2>473</d2>
<c2>2599</c2>
</quadruple>
<quadruple>
<d1>473</d1>
<c1>2835</c1>
<d2>524</d2>
<c2>963</c2>
</quadruple>
<quadruple>
<d1>524</d1>
<c1>607</c1>
<d2>553</d2>
<c2>2368</c2>
</quadruple>
<quadruple>
<d1>553</d1>
<c1>554</c1>
<d2>555</d2>
<c2>1582</c2>
</quadruple>
<quadruple>
<d1>555</d1>
<c1>602</c1>
<d2>585</d2>
<c2>524</c2>
</quadruple>
<quadruple>
<d1>585</d1>
<c1>1830</c1>
<d2>588</d2>
<c2>1778</c2>
</quadruple>
<quadruple>
<d1>588</d1>
<c1>867</c1>
<d2>645</d2>
<c2>2254</c2>
</quadruple>
<quadruple>
<d1>645</d1>
<c1>375</c1>
<d2>651</d2>
<c2>2847</c2>
</quadruple>
<quadruple>
<d1>651</d1>
<c1>2424</c1>
<d2>684</d2>
<c2>2894</c2>
</quadruple>
<quadruple>
<d1>684</d1>
<c1>1156</c1>
<d2>702</d2>
<c2>267</c2>
</quadruple>
<quadruple>
<d1>702</d1>
<c1>2952</c1>
<d2>759</d2>
<c2>202</c2>
</quadruple>
<quadruple>
<d1>759</d1>
<c1>2263</c1>
<d2>765</d2>
<c2>1939</c2>
</quadruple>
<quadruple>
<d1>765</d1>
<c1>1605</c1>
<d2>812</d2>
<c2>1993</c2>
</quadruple>
<quadruple>
<d1>812</d1>
<c1>1855</c1>
<d2>866</d2>
<c2>2854</c2>
</quadruple>
<quadruple>
<d1>866</d1>
<c1>1399</c1>
<d2>913</d2>
<c2>2679</c2>
</quadruple>
<quadruple>
<d1>913</d1>
<c1>1589</c1>
<d2>970</d2>
<c2>2395</c2>
</quadruple>
<quadruple>
<d1>970</d1>
<c1>963</c1>
<d2>1019</d2>
<c2>515</c2>
</quadruple>
<quadruple>
<d1>1019</d1>
<c1>590</c1>
<d2>1046</d2>
<c2>1585</c2>
</quadruple>
<quadruple>
<d1>1046</d1>
<c1>353</c1>
<d2>1101</d2>
<c2>99</c2>
</quadruple>
<quadruple>
<d1>1101</d1>
<c1>683</c1>
<d2>1106</d2>
<c2>1834</c2>
</quadruple>
<quadruple>
<d1>1106</d1>
<c1>1998</c1>
<d2>1109</d2>
<c2>2049</c2>
</quadruple>
<quadruple>
<d1>1109</d1>
<c1>283</c1>
<d2>1130</d2>
<c2>671</c2>
</quadruple>
<quadruple>
<d1>1130</d1>
<c1>565</c1>
<d2>1175</d2>
<c2>2305</c2>
</quadruple>
<quadruple>
<d1>1175</d1>
<c1>1519</c1>
<d2>1183</d2>
<c2>1290</c2>
</quadruple>
<quadruple>
<d1>1183</d1>
<c1>2178</c1>
<d2>1229</d2>
<c2>2944</c2>
</quadruple>
<quadruple>
<d1>1229</d1>
<c1>1823</c1>
<d2>1281</d2>
<c2>2457</c2>
</quadruple>
<quadruple>
<d1>1281</d1>
<c1>55</c1>
<d2>1299</d2>
<c2>2672</c2>
</quadruple>
<quadruple>
<d1>1299</d1>
<c1>710</c1>
<d2>1349</d2>
<c2>1665</c2>
</quadruple>
<quadruple>
<d1>1349</d1>
<c1>702</c1>
<d2>1394</d2>
<c2>2422</c2>
</quadruple>
<quadruple>
<d1>1394</d1>
<c1>1092</c1>
<d2>1406</d2>
<c2>1643</c2>
</quadruple>
<quadruple>
<d1>1406</d1>
<c1>984</c1>
<d2>1453</d2>
<c2>1346</c2>
</quadruple>
<quadruple>
<d1>1453</d1>
<c1>1114</c1>
<d2>1455</d2>
<c2>1943</c2>
</quadruple>
<quadruple>
<d1>1455</d1>
<c1>2783</c1>
<d2>1503</d2>
<c2>543</c2>
</quadruple>
<quadruple>
<d1>1503</d1>
<c1>2296</c1>
<d2>1507</d2>
<c2>41</c2>
</quadruple>
<quadruple>
<d1>1507</d1>
<c1>2772</c1>
<d2>3009</d2>
<c2>1882</c2>
</quadruple>
</left>
<right xsi:type="basicService" identifier="140">
<quadruple>
<d1>6</d1>
<c1>1377</c1>
<d2>19</d2>
<c2>2269</c2>
</quadruple>
<quadruple>
<d1>19</d1>
<c1>2224</c1>
<d2>28</d2>
<c2>2874</c2>
</quadruple>
<quadruple>
<d1>28</d1>
<c1>1522</c1>
<d2>53</d2>
<c2>2271</c2>
</quadruple>
<quadruple>
<d1>53</d1>
<c1>2117</c1>
<d2>92</d2>
<c2>1295</c2>
</quadruple>
<quadruple>
<d1>92</d1>
<c1>90</c1>
<d2>149</d2>
<c2>2230</c2>
</quadruple>
<quadruple>
<d1>149</d1>
<c1>1112</c1>
<d2>177</d2>
<c2>921</c2>
</quadruple>
<quadruple>
<d1>177</d1>
<c1>2230</c1>
<d2>205</d2>
<c2>2265</c2>
</quadruple>
<quadruple>
<d1>205</d1>
<c1>1364</c1>
<d2>224</d2>
<c2>2291</c2>
</quadruple>
<quadruple>
<d1>224</d1>
<c1>1491</c1>
<d2>241</d2>
<c2>2390</c2>
</quadruple>
<quadruple>
<d1>241</d1>
<c1>581</c1>
<d2>257</d2>
<c2>2559</c2>
</quadruple>
<quadruple>
<d1>257</d1>
<c1>130</c1>
<d2>275</d2>
<c2>285</c2>
</quadruple>
<quadruple>
<d1>275</d1>
<c1>1807</c1>
<d2>290</d2>
<c2>24</c2>
</quadruple>
<quadruple>
<d1>290</d1>
<c1>1100</c1>
<d2>307</d2>
<c2>501</c2>
</quadruple>
<quadruple>
<d1>307</d1>
<c1>1936</c1>
<d2>342</d2>
<c2>875</c2>
</quadruple>
<quadruple>
<d1>342</d1>
<c1>2816</c1>
<d2>351</d2>
<c2>2865</c2>
</quadruple>
<quadruple>
<d1>351</d1>
<c1>2335</c1>
<d2>399</d2>
<c2>848</c2>
</quadruple>
<quadruple>
<d1>399</d1>
<c1>960</c1>
<d2>438</d2>
<c2>321</c2>
</quadruple>
<quadruple>
<d1>438</d1>
<c1>2147</c1>
<d2>493</d2>
<c2>2390</c2>
</quadruple>
<quadruple>
<d1>493</d1>
<c1>1064</c1>
<d2>510</d2>
<c2>2127</c2>
</quadruple>
<quadruple>
<d1>510</d1>
<c1>1139</c1>
<d2>541</d2>
<c2>1295</c2>
</quadruple>
<quadruple>
<d1>541</d1>
<c1>2578</c1>
<d2>566</d2>
<c2>2891</c2>
</quadruple>
<quadruple>
<d1>566</d1>
<c1>2478</c1>
<d2>570</d2>
<c2>782</c2>
</quadruple>
<quadruple>
<d1>570</d1>
<c1>2294</c1>
<d2>586</d2>
<c2>1718</c2>
</quadruple>
<quadruple>
<d1>586</d1>
<c1>2112</c1>
<d2>634</d2>
<c2>2048</c2>
</quadruple>
<quadruple>
<d1>634</d1>
<c1>2422</c1>
<d2>677</d2>
<c2>530</c2>
</quadruple>
<quadruple>
<d1>677</d1>
<c1>2872</c1>
<d2>722</d2>
<c2>429</c2>
</quadruple>
<quadruple>
<d1>722</d1>
<c1>130</c1>
<d2>770</d2>
<c2>1003</c2>
</quadruple>
<quadruple>
<d1>770</d1>
<c1>1337</c1>
<d2>814</d2>
<c2>623</c2>
</quadruple>
<quadruple>
<d1>814</d1>
<c1>1439</c1>
<d2>873</d2>
<c2>201</c2>
</quadruple>
<quadruple>
<d1>873</d1>
<c1>2384</c1>
<d2>898</d2>
<c2>629</c2>
</quadruple>
<quadruple>
<d1>898</d1>
<c1>2558</c1>
<d2>951</d2>
<c2>1578</c2>
</quadruple>
<quadruple>
<d1>951</d1>
<c1>2835</c1>
<d2>992</d2>
<c2>147</c2>
</quadruple>
<quadruple>
<d1>992</d1>
<c1>131</c1>
<d2>997</d2>
<c2>993</c2>
</quadruple>
<quadruple>
<d1>997</d1>
<c1>1607</c1>
<d2>1019</d2>
<c2>2363</c2>
</quadruple>
<quadruple>
<d1>1019</d1>
<c1>2512</c1>
<d2>1057</d2>
<c2>225</c2>
</quadruple>
<quadruple>
<d1>1057</d1>
<c1>2785</c1>
<d2>1077</d2>
<c2>798</c2>
</quadruple>
<quadruple>
<d1>1077</d1>
<c1>1351</c1>
<d2>1104</d2>
<c2>23</c2>
</quadruple>
<quadruple>
<d1>1104</d1>
<c1>782</c1>
<d2>1109</d2>
<c2>166</c2>
</quadruple>
<quadruple>
<d1>1109</d1>
<c1>1047</c1>
<d2>1140</d2>
<c2>1285</c2>
</quadruple>
<quadruple>
<d1>1140</d1>
<c1>2673</c1>
<d2>1150</d2>
<c2>108</c2>
</quadruple>
<quadruple>
<d1>1150</d1>
<c1>578</c1>
<d2>1153</d2>
<c2>2683</c2>
</quadruple>
<quadruple>
<d1>1153</d1>
<c1>1095</c1>
<d2>1208</d2>
<c2>2538</c2>
</quadruple>
<quadruple>
<d1>1208</d1>
<c1>238</c1>
<d2>1250</d2>
<c2>137</c2>
</quadruple>
<quadruple>
<d1>1250</d1>
<c1>940</c1>
<d2>1296</d2>
<c2>1708</c2>
</quadruple>
<quadruple>
<d1>1296</d1>
<c1>654</c1>
<d2>1302</d2>
<c2>831</c2>
</quadruple>
<quadruple>
<d1>1302</d1>
<c1>1461</c1>
<d2>1353</d2>
<c2>40</c2>
</quadruple>
<quadruple>
<d1>1353</d1>
<c1>1573</c1>
<d2>1365</d2>
<c2>996</c2>
</quadruple>
<quadruple>
<d1>1365</d1>
<c1>2894</c1>
<d2>1368</d2>
<c2>514</c2>
</quadruple>
<quadruple>
<d1>1368</d1>
<c1>975</c1>
<d2>1379</d2>
<c2>1364</c2>
</quadruple>
<quadruple>
<d1>1379</d1>
<c1>1965</c1>
<d2>3009</d2>
<c2>2039</c2>
</quadruple>
</right>
</node>
</tree>