<?xml version="1.0" encoding="UTF-8" ?>

<tree xmlns:xsi="http://www.w3.org/2001/XMLSchema-instance"
      xsi:noNamespaceSchemaLocation="../../TCP.xsd">
<node xsi:type="constructor" type="XORC">
<left xsi:type="basicService" identifier="89">
<quadruple>
<d1>9</d1>
<c1>398</c1>
<d2>68</d2>
<c2>1138</c2>
</quadruple>
<quadruple>
<d1>68</d1>
<c1>1203</c1>
<d2>153</d2>
<c2>748</c2>
</quadruple>
<quadruple>
<d1>153</d1>
<c1>428</c1>
<d2>232</d2>
<c2>1612</c2>
</quadruple>
<quadruple>
<d1>232</d1>
<c1>1245</c1>
<d2>261</d2>
<c2>680</c2>
</quadruple>
<quadruple>
<d1>261</d1>
<c1>452</c1>
<d2>319</d2>
<c2>891</c2>
</quadruple>
<quadruple>
<d1>319</d1>
<c1>1051</c1>
<d2>360</d2>
<c2>116</c2>
</quadruple>
<quadruple>
<d1>360</d1>
<c1>306</c1>
<d2>430</d2>
<c2>1531</c2>
</quadruple>
<quadruple>
<d1>430</d1>
<c1>438</c1>
<d2>489</d2>
<c2>859</c2>
</quadruple>
<quadruple>
<d1>489</d1>
<c1>399</c1>
<d2>559</d2>
<c2>455</c2>
</quadruple>
<quadruple>
<d1>559</d1>
<c1>189</c1>
<d2>620</d2>
<c2>727</c2>
</quadruple>
<quadruple>
<d1>620</d1>
<c1>1232</c1>
<d2>695</d2>
<c2>638</c2>
</quadruple>
<quadruple>
<d1>695</d1>
<c1>240</c1>
<d2>748</d2>
<c2>1029</c2>
</quadruple>
<quadruple>
<d1>748</d1>
<c1>1280</c1>
<d2>832</d2>
<c2>600</c2>
</quadruple>
<quadruple>
<d1>832</d1>
<c1>178</c1>
<d2>871</d2>
<c2>1399</c2>
</quadruple>
<quadruple>
<d1>871</d1>
<c1>256</c1>
<d2>919</d2>
<c2>122</c2>
</quadruple>
<quadruple>
<d1>919</d1>
<c1>1621</c1>
<d2>965</d2>
<c2>606</c2>
</quadruple>
<quadruple>
<d1>965</d1>
<c1>784</c1>
<d2>1007</d2>
<c2>583</c2>
</quadruple>
<quadruple>
<d1>1007</d1>
<c1>1055</c1>
<d2>1014</d2>
<c2>350</c2>
</quadruple>
<quadruple>
<d1>1014</d1>
<c1>1353</c1>
<d2>1092</d2>
<c2>1522</c2>
</quadruple>
<quadruple>
<d1>1092</d1>
<c1>1544</c1>
<d2>1804</d2>
<c2>1068</c2>
</quadruple>
</left>
<right xsi:type="basicService" identifier="90">
<quadruple>
<d1>9</d1>
<c1>172</c1>
<d2>79</d2>
<c2>1592</c2>
</quadruple>
<quadruple>
<d1>79</d1>
<c1>511</c1>
<d2>104</d2>
<c2>1732</c2>
</quadruple>
<quadruple>
<d1>104</d1>
<c1>1342</c1>
<d2>125</d2>
<c2>1557</c2>
</quadruple>
<quadruple>
<d1>125</d1>
<c1>410</c1>
<d2>172</d2>
<c2>594</c2>
</quadruple>
<quadruple>
<d1>172</d1>
<c1>911</c1>
<d2>204</d2>
<c2>1547</c2>
</quadruple>
<quadruple>
<d1>204</d1>
<c1>510</c1>
<d2>264</d2>
<c2>860</c2>
</quadruple>
<quadruple>
<d1>264</d1>
<c1>1351</c1>
<d2>297</d2>
<c2>798</c2>
</quadruple>
<quadruple>
<d1>297</d1>
<c1>1810</c1>
<d2>385</d2>
<c2>814</c2>
</quadruple>
<quadruple>
<d1>385</d1>
<c1>1659</c1>
<d2>408</d2>
<c2>161</c2>
</quadruple>
<quadruple>
<d1>408</d1>
<c1>1011</c1>
<d2>477</d2>
<c2>1350</c2>
</quadruple>
<quadruple>
<d1>477</d1>
<c1>1669</c1>
<d2>509</d2>
<c2>1325</c2>
</quadruple>
<quadruple>
<d1>509</d1>
<c1>1329</c1>
<d2>568</d2>
<c2>1107</c2>
</quadruple>
<quadruple>
<d1>568</d1>
<c1>1642</c1>
<d2>653</d2>
<c2>1336</c2>
</quadruple>
<quadruple>
<d1>653</d1>
<c1>853</c1>
<d2>664</d2>
<c2>1057</c2>
</quadruple>
<quadruple>
<d1>664</d1>
<c1>456</c1>
<d2>730</d2>
<c2>1149</c2>
</quadruple>
<quadruple>
<d1>730</d1>
<c1>973</c1>
<d2>748</d2>
<c2>926</c2>
</quadruple>
<quadruple>
<d1>748</d1>
<c1>162</c1>
<d2>803</d2>
<c2>1506</c2>
</quadruple>
<quadruple>
<d1>803</d1>
<c1>943</c1>
<d2>848</d2>
<c2>1559</c2>
</quadruple>
<quadruple>
<d1>848</d1>
<c1>771</c1>
<d2>875</d2>
<c2>1611</c2>
</quadruple>
<quadruple>
<d1>875</d1>
<c1>911</c1>
<d2>1804</d2>
<c2>1212</c2>
</quadruple>
</right>
</node>
</tree>