<?xml version="1.0" encoding="UTF-8" ?>

<tree xmlns:xsi="http://www.w3.org/2001/XMLSchema-instance"
      xsi:noNamespaceSchemaLocation="../../TCP.xsd">
<node xsi:type="constructor" type="XORC">
<left xsi:type="basicService" identifier="103">
<quadruple>
<d1>10</d1>
<c1>938</c1>
<d2>49</d2>
<c2>1636</c2>
</quadruple>
<quadruple>
<d1>49</d1>
<c1>1862</c1>
<d2>123</d2>
<c2>1553</c2>
</quadruple>
<quadruple>
<d1>123</d1>
<c1>1166</c1>
<d2>219</d2>
<c2>1330</c2>
</quadruple>
<quadruple>
<d1>219</d1>
<c1>395</c1>
<d2>249</d2>
<c2>1845</c2>
</quadruple>
<quadruple>
<d1>249</d1>
<c1>1314</c1>
<d2>344</d2>
<c2>870</c2>
</quadruple>
<quadruple>
<d1>344</d1>
<c1>278</c1>
<d2>426</d2>
<c2>123</c2>
</quadruple>
<quadruple>
<d1>426</d1>
<c1>1965</c1>
<d2>485</d2>
<c2>631</c2>
</quadruple>
<quadruple>
<d1>485</d1>
<c1>1024</c1>
<d2>556</d2>
<c2>1090</c2>
</quadruple>
<quadruple>
<d1>556</d1>
<c1>769</c1>
<d2>580</d2>
<c2>251</c2>
</quadruple>
<quadruple>
<d1>580</d1>
<c1>1683</c1>
<d2>647</d2>
<c2>1500</c2>
</quadruple>
<quadruple>
<d1>647</d1>
<c1>882</c1>
<d2>656</d2>
<c2>1208</c2>
</quadruple>
<quadruple>
<d1>656</d1>
<c1>1059</c1>
<d2>702</d2>
<c2>38</c2>
</quadruple>
<quadruple>
<d1>702</d1>
<c1>1976</c1>
<d2>734</d2>
<c2>1159</c2>
</quadruple>
<quadruple>
<d1>734</d1>
<c1>1371</c1>
<d2>742</d2>
<c2>198</c2>
</quadruple>
<quadruple>
<d1>742</d1>
<c1>487</c1>
<d2>820</d2>
<c2>1722</c2>
</quadruple>
<quadruple>
<d1>820</d1>
<c1>1471</c1>
<d2>909</d2>
<c2>693</c2>
</quadruple>
<quadruple>
<d1>909</d1>
<c1>73</c1>
<d2>944</d2>
<c2>576</c2>
</quadruple>
<quadruple>
<d1>944</d1>
<c1>1451</c1>
<d2>996</d2>
<c2>650</c2>
</quadruple>
<quadruple>
<d1>996</d1>
<c1>937</c1>
<d2>1024</d2>
<c2>661</c2>
</quadruple>
<quadruple>
<d1>1024</d1>
<c1>307</c1>
<d2>2003</d2>
<c2>1281</c2>
</quadruple>
</left>
<right xsi:type="basicService" identifier="104">
<quadruple>
<d1>10</d1>
<c1>900</c1>
<d2>53</d2>
<c2>567</c2>
</quadruple>
<quadruple>
<d1>53</d1>
<c1>1003</c1>
<d2>105</d2>
<c2>816</c2>
</quadruple>
<quadruple>
<d1>105</d1>
<c1>847</c1>
<d2>141</d2>
<c2>154</c2>
</quadruple>
<quadruple>
<d1>141</d1>
<c1>706</c1>
<d2>217</d2>
<c2>820</c2>
</quadruple>
<quadruple>
<d1>217</d1>
<c1>496</c1>
<d2>269</d2>
<c2>89</c2>
</quadruple>
<quadruple>
<d1>269</d1>
<c1>1133</c1>
<d2>285</d2>
<c2>1313</c2>
</quadruple>
<quadruple>
<d1>285</d1>
<c1>478</c1>
<d2>296</d2>
<c2>1799</c2>
</quadruple>
<quadruple>
<d1>296</d1>
<c1>1945</c1>
<d2>343</d2>
<c2>1714</c2>
</quadruple>
<quadruple>
<d1>343</d1>
<c1>968</c1>
<d2>386</d2>
<c2>916</c2>
</quadruple>
<quadruple>
<d1>386</d1>
<c1>1938</c1>
<d2>467</d2>
<c2>218</c2>
</quadruple>
<quadruple>
<d1>467</d1>
<c1>1175</c1>
<d2>533</d2>
<c2>692</c2>
</quadruple>
<quadruple>
<d1>533</d1>
<c1>1153</c1>
<d2>620</d2>
<c2>1921</c2>
</quadruple>
<quadruple>
<d1>620</d1>
<c1>1855</c1>
<d2>673</d2>
<c2>1158</c2>
</quadruple>
<quadruple>
<d1>673</d1>
<c1>432</c1>
<d2>693</d2>
<c2>30</c2>
</quadruple>
<quadruple>
<d1>693</d1>
<c1>719</c1>
<d2>783</d2>
<c2>1186</c2>
</quadruple>
<quadruple>
<d1>783</d1>
<c1>1204</c1>
<d2>882</d2>
<c2>92</c2>
</quadruple>
<quadruple>
<d1>882</d1>
<c1>1639</c1>
<d2>959</d2>
<c2>620</c2>
</quadruple>
<quadruple>
<d1>959</d1>
<c1>1792</c1>
<d2>1048</d2>
<c2>274</c2>
</quadruple>
<quadruple>
<d1>1048</d1>
<c1>426</c1>
<d2>1086</d2>
<c2>518</c2>
</quadruple>
<quadruple>
<d1>1086</d1>
<c1>1031</c1>
<d2>2003</d2>
<c2>1760</c2>
</quadruple>
</right>
</node>
</tree>