<?xml version="1.0" encoding="UTF-8" ?>

<tree xmlns:xsi="http://www.w3.org/2001/XMLSchema-instance"
      xsi:noNamespaceSchemaLocation="../../TCP.xsd">
<node xsi:type="constructor" type="XORD">
<left xsi:type="basicService" identifier="81">
<quadruple>
<d1>5</d1>
<c1>902</c1>
<d2>17</d2>
<c2>7</c2>
</quadruple>
<quadruple>
<d1>17</d1>
<c1>2465</c1>
<d2>29</d2>
<c2>46</c2>
</quadruple>
<quadruple>
<d1>29</d1>
<c1>1429</c1>
<d2>31</d2>
<c2>2112</c2>
</quadruple>
<quadruple>
<d1>31</d1>
<c1>1203</c1>
<d2>37</d2>
<c2>2109</c2>
</quadruple>
<quadruple>
<d1>37</d1>
<c1>1586</c1>
<d2>70</d2>
<c2>100</c2>
</quadruple>
<quadruple>
<d1>70</d1>
<c1>855</c1>
<d2>103</d2>
<c2>230</c2>
</quadruple>
<quadruple>
<d1>103</d1>
<c1>915</c1>
<d2>143</d2>
<c2>1654</c2>
</quadruple>
<quadruple>
<d1>143</d1>
<c1>337</c1>
<d2>175</d2>
<c2>1133</c2>
</quadruple>
<quadruple>
<d1>175</d1>
<c1>1339</c1>
<d2>183</d2>
<c2>2071</c2>
</quadruple>
<quadruple>
<d1>183</d1>
<c1>2442</c1>
<d2>204</d2>
<c2>1476</c2>
</quadruple>
<quadruple>
<d1>204</d1>
<c1>1888</c1>
<d2>224</d2>
<c2>68</c2>
</quadruple>
<quadruple>
<d1>224</d1>
<c1>1568</c1>
<d2>250</d2>
<c2>569</c2>
</quadruple>
<quadruple>
<d1>250</d1>
<c1>781</c1>
<d2>282</d2>
<c2>1964</c2>
</quadruple>
<quadruple>
<d1>282</d1>
<c1>551</c1>
<d2>304</d2>
<c2>1962</c2>
</quadruple>
<quadruple>
<d1>304</d1>
<c1>1977</c1>
<d2>352</d2>
<c2>310</c2>
</quadruple>
<quadruple>
<d1>352</d1>
<c1>1280</c1>
<d2>359</d2>
<c2>1750</c2>
</quadruple>
<quadruple>
<d1>359</d1>
<c1>1776</c1>
<d2>400</d2>
<c2>1673</c2>
</quadruple>
<quadruple>
<d1>400</d1>
<c1>1773</c1>
<d2>410</d2>
<c2>1880</c2>
</quadruple>
<quadruple>
<d1>410</d1>
<c1>793</c1>
<d2>417</d2>
<c2>708</c2>
</quadruple>
<quadruple>
<d1>417</d1>
<c1>2173</c1>
<d2>433</d2>
<c2>2164</c2>
</quadruple>
<quadruple>
<d1>433</d1>
<c1>1029</c1>
<d2>469</d2>
<c2>1841</c2>
</quadruple>
<quadruple>
<d1>469</d1>
<c1>1559</c1>
<d2>478</d2>
<c2>70</c2>
</quadruple>
<quadruple>
<d1>478</d1>
<c1>2482</c1>
<d2>509</d2>
<c2>354</c2>
</quadruple>
<quadruple>
<d1>509</d1>
<c1>1722</c1>
<d2>533</d2>
<c2>1060</c2>
</quadruple>
<quadruple>
<d1>533</d1>
<c1>2477</c1>
<d2>583</d2>
<c2>960</c2>
</quadruple>
<quadruple>
<d1>583</d1>
<c1>1261</c1>
<d2>585</d2>
<c2>962</c2>
</quadruple>
<quadruple>
<d1>585</d1>
<c1>249</c1>
<d2>612</d2>
<c2>1782</c2>
</quadruple>
<quadruple>
<d1>612</d1>
<c1>1010</c1>
<d2>654</d2>
<c2>695</c2>
</quadruple>
<quadruple>
<d1>654</d1>
<c1>1228</c1>
<d2>704</d2>
<c2>480</c2>
</quadruple>
<quadruple>
<d1>704</d1>
<c1>1312</c1>
<d2>718</d2>
<c2>556</c2>
</quadruple>
<quadruple>
<d1>718</d1>
<c1>274</c1>
<d2>745</d2>
<c2>615</c2>
</quadruple>
<quadruple>
<d1>745</d1>
<c1>229</c1>
<d2>760</d2>
<c2>97</c2>
</quadruple>
<quadruple>
<d1>760</d1>
<c1>808</c1>
<d2>782</d2>
<c2>1352</c2>
</quadruple>
<quadruple>
<d1>782</d1>
<c1>1664</c1>
<d2>796</d2>
<c2>626</c2>
</quadruple>
<quadruple>
<d1>796</d1>
<c1>982</c1>
<d2>840</d2>
<c2>2153</c2>
</quadruple>
<quadruple>
<d1>840</d1>
<c1>132</c1>
<d2>883</d2>
<c2>2156</c2>
</quadruple>
<quadruple>
<d1>883</d1>
<c1>2283</c1>
<d2>927</d2>
<c2>256</c2>
</quadruple>
<quadruple>
<d1>927</d1>
<c1>757</c1>
<d2>946</d2>
<c2>732</c2>
</quadruple>
<quadruple>
<d1>946</d1>
<c1>2460</c1>
<d2>967</d2>
<c2>622</c2>
</quadruple>
<quadruple>
<d1>967</d1>
<c1>1859</c1>
<d2>980</d2>
<c2>94</c2>
</quadruple>
<quadruple>
<d1>980</d1>
<c1>2054</c1>
<d2>991</d2>
<c2>1188</c2>
</quadruple>
<quadruple>
<d1>991</d1>
<c1>1012</c1>
<d2>1026</d2>
<c2>1069</c2>
</quadruple>
<quadruple>
<d1>1026</d1>
<c1>1157</c1>
<d2>1035</d2>
<c2>1550</c2>
</quadruple>
<quadruple>
<d1>1035</d1>
<c1>907</c1>
<d2>1066</d2>
<c2>1464</c2>
</quadruple>
<quadruple>
<d1>1066</d1>
<c1>1342</c1>
<d2>1081</d2>
<c2>2419</c2>
</quadruple>
<quadruple>
<d1>1081</d1>
<c1>1973</c1>
<d2>1099</d2>
<c2>145</c2>
</quadruple>
<quadruple>
<d1>1099</d1>
<c1>340</c1>
<d2>1101</d2>
<c2>66</c2>
</quadruple>
<quadruple>
<d1>1101</d1>
<c1>2225</c1>
<d2>1138</d2>
<c2>786</c2>
</quadruple>
<quadruple>
<d1>1138</d1>
<c1>22</c1>
<d2>1164</d2>
<c2>651</c2>
</quadruple>
<quadruple>
<d1>1164</d1>
<c1>1990</c1>
<d2>2506</d2>
<c2>2497</c2>
</quadruple>
</left>
<right xsi:type="basicService" identifier="82">
<quadruple>
<d1>5</d1>
<c1>98</c1>
<d2>35</d2>
<c2>1416</c2>
</quadruple>
<quadruple>
<d1>35</d1>
<c1>1906</c1>
<d2>77</d2>
<c2>888</c2>
</quadruple>
<quadruple>
<d1>77</d1>
<c1>2243</c1>
<d2>90</d2>
<c2>1804</c2>
</quadruple>
<quadruple>
<d1>90</d1>
<c1>283</c1>
<d2>99</d2>
<c2>2095</c2>
</quadruple>
<quadruple>
<d1>99</d1>
<c1>1392</c1>
<d2>122</d2>
<c2>43</c2>
</quadruple>
<quadruple>
<d1>122</d1>
<c1>501</c1>
<d2>154</d2>
<c2>617</c2>
</quadruple>
<quadruple>
<d1>154</d1>
<c1>2189</c1>
<d2>198</d2>
<c2>1150</c2>
</quadruple>
<quadruple>
<d1>198</d1>
<c1>1472</c1>
<d2>246</d2>
<c2>1096</c2>
</quadruple>
<quadruple>
<d1>246</d1>
<c1>473</c1>
<d2>294</d2>
<c2>2179</c2>
</quadruple>
<quadruple>
<d1>294</d1>
<c1>1705</c1>
<d2>319</d2>
<c2>1141</c2>
</quadruple>
<quadruple>
<d1>319</d1>
<c1>1912</c1>
<d2>333</d2>
<c2>266</c2>
</quadruple>
<quadruple>
<d1>333</d1>
<c1>1275</c1>
<d2>337</d2>
<c2>1546</c2>
</quadruple>
<quadruple>
<d1>337</d1>
<c1>907</c1>
<d2>387</d2>
<c2>2234</c2>
</quadruple>
<quadruple>
<d1>387</d1>
<c1>1000</c1>
<d2>435</d2>
<c2>381</c2>
</quadruple>
<quadruple>
<d1>435</d1>
<c1>85</c1>
<d2>470</d2>
<c2>2358</c2>
</quadruple>
<quadruple>
<d1>470</d1>
<c1>2074</c1>
<d2>520</d2>
<c2>503</c2>
</quadruple>
<quadruple>
<d1>520</d1>
<c1>628</c1>
<d2>527</d2>
<c2>181</c2>
</quadruple>
<quadruple>
<d1>527</d1>
<c1>442</c1>
<d2>558</d2>
<c2>1972</c2>
</quadruple>
<quadruple>
<d1>558</d1>
<c1>302</c1>
<d2>579</d2>
<c2>473</c2>
</quadruple>
<quadruple>
<d1>579</d1>
<c1>1128</c1>
<d2>606</d2>
<c2>1564</c2>
</quadruple>
<quadruple>
<d1>606</d1>
<c1>563</c1>
<d2>645</d2>
<c2>908</c2>
</quadruple>
<quadruple>
<d1>645</d1>
<c1>181</c1>
<d2>683</d2>
<c2>2185</c2>
</quadruple>
<quadruple>
<d1>683</d1>
<c1>1184</c1>
<d2>689</d2>
<c2>396</c2>
</quadruple>
<quadruple>
<d1>689</d1>
<c1>1964</c1>
<d2>708</d2>
<c2>233</c2>
</quadruple>
<quadruple>
<d1>708</d1>
<c1>2410</c1>
<d2>753</d2>
<c2>144</c2>
</quadruple>
<quadruple>
<d1>753</d1>
<c1>842</c1>
<d2>795</d2>
<c2>2277</c2>
</quadruple>
<quadruple>
<d1>795</d1>
<c1>434</c1>
<d2>833</d2>
<c2>1757</c2>
</quadruple>
<quadruple>
<d1>833</d1>
<c1>2038</c1>
<d2>862</d2>
<c2>272</c2>
</quadruple>
<quadruple>
<d1>862</d1>
<c1>1314</c1>
<d2>887</d2>
<c2>585</c2>
</quadruple>
<quadruple>
<d1>887</d1>
<c1>81</c1>
<d2>937</d2>
<c2>242</c2>
</quadruple>
<quadruple>
<d1>937</d1>
<c1>1824</c1>
<d2>983</d2>
<c2>1162</c2>
</quadruple>
<quadruple>
<d1>983</d1>
<c1>2248</c1>
<d2>1019</d2>
<c2>1367</c2>
</quadruple>
<quadruple>
<d1>1019</d1>
<c1>2420</c1>
<d2>1052</d2>
<c2>1935</c2>
</quadruple>
<quadruple>
<d1>1052</d1>
<c1>2143</c1>
<d2>1074</d2>
<c2>1057</c2>
</quadruple>
<quadruple>
<d1>1074</d1>
<c1>770</c1>
<d2>1101</d2>
<c2>1773</c2>
</quadruple>
<quadruple>
<d1>1101</d1>
<c1>1808</c1>
<d2>1125</d2>
<c2>599</c2>
</quadruple>
<quadruple>
<d1>1125</d1>
<c1>944</c1>
<d2>1149</d2>
<c2>693</c2>
</quadruple>
<quadruple>
<d1>1149</d1>
<c1>480</c1>
<d2>1193</d2>
<c2>1283</c2>
</quadruple>
<quadruple>
<d1>1193</d1>
<c1>29</c1>
<d2>1211</d2>
<c2>2260</c2>
</quadruple>
<quadruple>
<d1>1211</d1>
<c1>2301</c1>
<d2>1228</d2>
<c2>306</c2>
</quadruple>
<quadruple>
<d1>1228</d1>
<c1>1825</c1>
<d2>1266</d2>
<c2>1251</c2>
</quadruple>
<quadruple>
<d1>1266</d1>
<c1>906</c1>
<d2>1287</d2>
<c2>740</c2>
</quadruple>
<quadruple>
<d1>1287</d1>
<c1>1448</c1>
<d2>1335</d2>
<c2>1993</c2>
</quadruple>
<quadruple>
<d1>1335</d1>
<c1>1963</c1>
<d2>1357</d2>
<c2>984</c2>
</quadruple>
<quadruple>
<d1>1357</d1>
<c1>1028</c1>
<d2>1369</d2>
<c2>2137</c2>
</quadruple>
<quadruple>
<d1>1369</d1>
<c1>456</c1>
<d2>1399</d2>
<c2>2444</c2>
</quadruple>
<quadruple>
<d1>1399</d1>
<c1>1078</c1>
<d2>1406</d2>
<c2>691</c2>
</quadruple>
<quadruple>
<d1>1406</d1>
<c1>754</c1>
<d2>1449</d2>
<c2>2462</c2>
</quadruple>
<quadruple>
<d1>1449</d1>
<c1>2502</c1>
<d2>1470</d2>
<c2>186</c2>
</quadruple>
<quadruple>
<d1>1470</d1>
<c1>1434</c1>
<d2>2506</d2>
<c2>966</c2>
</quadruple>
</right>
</node>
</tree>