<?xml version="1.0" encoding="UTF-8" ?>

<tree xmlns:xsi="http://www.w3.org/2001/XMLSchema-instance"
      xsi:noNamespaceSchemaLocation="../../TCP.xsd">
<node xsi:type="constructor" type="SYNCAND">
<left xsi:type="basicService" identifier="185">
<quadruple>
<d1>12</d1>
<c1>548</c1>
<d2>95</d2>
<c2>4883</c2>
</quadruple>
<quadruple>
<d1>95</d1>
<c1>5954</c1>
<d2>132</d2>
<c2>5906</c2>
</quadruple>
<quadruple>
<d1>132</d1>
<c1>2386</c1>
<d2>168</d2>
<c2>4375</c2>
</quadruple>
<quadruple>
<d1>168</d1>
<c1>3934</c1>
<d2>210</d2>
<c2>1532</c2>
</quadruple>
<quadruple>
<d1>210</d1>
<c1>269</c1>
<d2>297</d2>
<c2>4484</c2>
</quadruple>
<quadruple>
<d1>297</d1>
<c1>4677</c1>
<d2>306</d2>
<c2>4859</c2>
</quadruple>
<quadruple>
<d1>306</d1>
<c1>3020</c1>
<d2>412</d2>
<c2>781</c2>
</quadruple>
<quadruple>
<d1>412</d1>
<c1>3237</c1>
<d2>452</d2>
<c2>5722</c2>
</quadruple>
<quadruple>
<d1>452</d1>
<c1>5863</c1>
<d2>491</d2>
<c2>1536</c2>
</quadruple>
<quadruple>
<d1>491</d1>
<c1>1249</c1>
<d2>501</d2>
<c2>3810</c2>
</quadruple>
<quadruple>
<d1>501</d1>
<c1>4725</c1>
<d2>555</d2>
<c2>3942</c2>
</quadruple>
<quadruple>
<d1>555</d1>
<c1>4827</c1>
<d2>651</d2>
<c2>1652</c2>
</quadruple>
<quadruple>
<d1>651</d1>
<c1>595</c1>
<d2>715</d2>
<c2>3913</c2>
</quadruple>
<quadruple>
<d1>715</d1>
<c1>1612</c1>
<d2>820</d2>
<c2>3406</c2>
</quadruple>
<quadruple>
<d1>820</d1>
<c1>2955</c1>
<d2>927</d2>
<c2>3026</c2>
</quadruple>
<quadruple>
<d1>927</d1>
<c1>2956</c1>
<d2>940</d2>
<c2>633</c2>
</quadruple>
<quadruple>
<d1>940</d1>
<c1>1648</c1>
<d2>948</d2>
<c2>1733</c2>
</quadruple>
<quadruple>
<d1>948</d1>
<c1>169</c1>
<d2>1021</d2>
<c2>5008</c2>
</quadruple>
<quadruple>
<d1>1021</d1>
<c1>4430</c1>
<d2>1068</d2>
<c2>2516</c2>
</quadruple>
<quadruple>
<d1>1068</d1>
<c1>2670</c1>
<d2>1177</d2>
<c2>4930</c2>
</quadruple>
<quadruple>
<d1>1177</d1>
<c1>3964</c1>
<d2>1226</d2>
<c2>3519</c2>
</quadruple>
<quadruple>
<d1>1226</d1>
<c1>2587</c1>
<d2>1270</d2>
<c2>4757</c2>
</quadruple>
<quadruple>
<d1>1270</d1>
<c1>5642</c1>
<d2>1358</d2>
<c2>4545</c2>
</quadruple>
<quadruple>
<d1>1358</d1>
<c1>4702</c1>
<d2>1472</d2>
<c2>1378</c2>
</quadruple>
<quadruple>
<d1>1472</d1>
<c1>4443</c1>
<d2>1561</d2>
<c2>2878</c2>
</quadruple>
<quadruple>
<d1>1561</d1>
<c1>3520</c1>
<d2>1672</d2>
<c2>76</c2>
</quadruple>
<quadruple>
<d1>1672</d1>
<c1>4272</c1>
<d2>1787</d2>
<c2>3958</c2>
</quadruple>
<quadruple>
<d1>1787</d1>
<c1>2353</c1>
<d2>1824</d2>
<c2>2602</c2>
</quadruple>
<quadruple>
<d1>1824</d1>
<c1>4676</c1>
<d2>1939</d2>
<c2>5828</c2>
</quadruple>
<quadruple>
<d1>1939</d1>
<c1>934</c1>
<d2>2057</d2>
<c2>3865</c2>
</quadruple>
<quadruple>
<d1>2057</d1>
<c1>2977</c1>
<d2>2133</d2>
<c2>1790</c2>
</quadruple>
<quadruple>
<d1>2133</d1>
<c1>3599</c1>
<d2>2198</d2>
<c2>5643</c2>
</quadruple>
<quadruple>
<d1>2198</d1>
<c1>4449</c1>
<d2>2265</d2>
<c2>5760</c2>
</quadruple>
<quadruple>
<d1>2265</d1>
<c1>3188</c1>
<d2>2369</d2>
<c2>4582</c2>
</quadruple>
<quadruple>
<d1>2369</d1>
<c1>2738</c1>
<d2>2381</d2>
<c2>4097</c2>
</quadruple>
<quadruple>
<d1>2381</d1>
<c1>1692</c1>
<d2>2432</d2>
<c2>3041</c2>
</quadruple>
<quadruple>
<d1>2432</d1>
<c1>3199</c1>
<d2>2461</d2>
<c2>2210</c2>
</quadruple>
<quadruple>
<d1>2461</d1>
<c1>4242</c1>
<d2>2503</d2>
<c2>3078</c2>
</quadruple>
<quadruple>
<d1>2503</d1>
<c1>4701</c1>
<d2>2561</d2>
<c2>5422</c2>
</quadruple>
<quadruple>
<d1>2561</d1>
<c1>1405</c1>
<d2>2659</d2>
<c2>2829</c2>
</quadruple>
<quadruple>
<d1>2659</d1>
<c1>626</c1>
<d2>2752</d2>
<c2>4680</c2>
</quadruple>
<quadruple>
<d1>2752</d1>
<c1>175</c1>
<d2>2815</d2>
<c2>2931</c2>
</quadruple>
<quadruple>
<d1>2815</d1>
<c1>3279</c1>
<d2>2848</d2>
<c2>5680</c2>
</quadruple>
<quadruple>
<d1>2848</d1>
<c1>5186</c1>
<d2>2915</d2>
<c2>3966</c2>
</quadruple>
<quadruple>
<d1>2915</d1>
<c1>2790</c1>
<d2>3000</d2>
<c2>1906</c2>
</quadruple>
<quadruple>
<d1>3000</d1>
<c1>2400</c1>
<d2>3019</d2>
<c2>801</c2>
</quadruple>
<quadruple>
<d1>3019</d1>
<c1>3153</c1>
<d2>3021</d2>
<c2>1588</c2>
</quadruple>
<quadruple>
<d1>3021</d1>
<c1>396</c1>
<d2>3027</d2>
<c2>2582</c2>
</quadruple>
<quadruple>
<d1>3027</d1>
<c1>129</c1>
<d2>3109</d2>
<c2>2390</c2>
</quadruple>
<quadruple>
<d1>3109</d1>
<c1>5840</c1>
<d2>6005</d2>
<c2>5124</c2>
</quadruple>
</left>
<right xsi:type="basicService" identifier="186">
<quadruple>
<d1>12</d1>
<c1>4534</c1>
<d2>27</d2>
<c2>5276</c2>
</quadruple>
<quadruple>
<d1>27</d1>
<c1>1421</c1>
<d2>92</d2>
<c2>3786</c2>
</quadruple>
<quadruple>
<d1>92</d1>
<c1>5491</c1>
<d2>195</d2>
<c2>832</c2>
</quadruple>
<quadruple>
<d1>195</d1>
<c1>1082</c1>
<d2>311</d2>
<c2>4045</c2>
</quadruple>
<quadruple>
<d1>311</d1>
<c1>1421</c1>
<d2>364</d2>
<c2>4084</c2>
</quadruple>
<quadruple>
<d1>364</d1>
<c1>2370</c1>
<d2>462</d2>
<c2>5010</c2>
</quadruple>
<quadruple>
<d1>462</d1>
<c1>1279</c1>
<d2>540</d2>
<c2>3802</c2>
</quadruple>
<quadruple>
<d1>540</d1>
<c1>734</c1>
<d2>651</d2>
<c2>2002</c2>
</quadruple>
<quadruple>
<d1>651</d1>
<c1>3513</c1>
<d2>653</d2>
<c2>3246</c2>
</quadruple>
<quadruple>
<d1>653</d1>
<c1>5553</c1>
<d2>747</d2>
<c2>2623</c2>
</quadruple>
<quadruple>
<d1>747</d1>
<c1>5731</c1>
<d2>826</d2>
<c2>1626</c2>
</quadruple>
<quadruple>
<d1>826</d1>
<c1>5692</c1>
<d2>866</d2>
<c2>5813</c2>
</quadruple>
<quadruple>
<d1>866</d1>
<c1>573</c1>
<d2>894</d2>
<c2>832</c2>
</quadruple>
<quadruple>
<d1>894</d1>
<c1>2345</c1>
<d2>992</d2>
<c2>5921</c2>
</quadruple>
<quadruple>
<d1>992</d1>
<c1>3064</c1>
<d2>1028</d2>
<c2>1155</c2>
</quadruple>
<quadruple>
<d1>1028</d1>
<c1>3495</c1>
<d2>1106</d2>
<c2>373</c2>
</quadruple>
<quadruple>
<d1>1106</d1>
<c1>947</c1>
<d2>1193</d2>
<c2>2695</c2>
</quadruple>
<quadruple>
<d1>1193</d1>
<c1>5588</c1>
<d2>1221</d2>
<c2>594</c2>
</quadruple>
<quadruple>
<d1>1221</d1>
<c1>241</c1>
<d2>1333</d2>
<c2>3913</c2>
</quadruple>
<quadruple>
<d1>1333</d1>
<c1>1266</c1>
<d2>1398</d2>
<c2>979</c2>
</quadruple>
<quadruple>
<d1>1398</d1>
<c1>3436</c1>
<d2>1423</d2>
<c2>4812</c2>
</quadruple>
<quadruple>
<d1>1423</d1>
<c1>1935</c1>
<d2>1454</d2>
<c2>405</c2>
</quadruple>
<quadruple>
<d1>1454</d1>
<c1>3376</c1>
<d2>1495</d2>
<c2>5625</c2>
</quadruple>
<quadruple>
<d1>1495</d1>
<c1>3337</c1>
<d2>1510</d2>
<c2>3969</c2>
</quadruple>
<quadruple>
<d1>1510</d1>
<c1>3988</c1>
<d2>1626</d2>
<c2>1106</c2>
</quadruple>
<quadruple>
<d1>1626</d1>
<c1>1736</c1>
<d2>1704</d2>
<c2>4748</c2>
</quadruple>
<quadruple>
<d1>1704</d1>
<c1>2049</c1>
<d2>1743</d2>
<c2>5673</c2>
</quadruple>
<quadruple>
<d1>1743</d1>
<c1>4424</c1>
<d2>1781</d2>
<c2>2837</c2>
</quadruple>
<quadruple>
<d1>1781</d1>
<c1>3130</c1>
<d2>1836</d2>
<c2>5203</c2>
</quadruple>
<quadruple>
<d1>1836</d1>
<c1>1556</c1>
<d2>1914</d2>
<c2>5379</c2>
</quadruple>
<quadruple>
<d1>1914</d1>
<c1>525</c1>
<d2>1940</d2>
<c2>1787</c2>
</quadruple>
<quadruple>
<d1>1940</d1>
<c1>4358</c1>
<d2>2005</d2>
<c2>5147</c2>
</quadruple>
<quadruple>
<d1>2005</d1>
<c1>1713</c1>
<d2>2080</d2>
<c2>4113</c2>
</quadruple>
<quadruple>
<d1>2080</d1>
<c1>2716</c1>
<d2>2085</d2>
<c2>609</c2>
</quadruple>
<quadruple>
<d1>2085</d1>
<c1>4489</c1>
<d2>2181</d2>
<c2>3396</c2>
</quadruple>
<quadruple>
<d1>2181</d1>
<c1>2147</c1>
<d2>2219</d2>
<c2>4979</c2>
</quadruple>
<quadruple>
<d1>2219</d1>
<c1>3913</c1>
<d2>2278</d2>
<c2>4132</c2>
</quadruple>
<quadruple>
<d1>2278</d1>
<c1>4168</c1>
<d2>2396</d2>
<c2>2461</c2>
</quadruple>
<quadruple>
<d1>2396</d1>
<c1>295</c1>
<d2>2419</d2>
<c2>2652</c2>
</quadruple>
<quadruple>
<d1>2419</d1>
<c1>1113</c1>
<d2>2501</d2>
<c2>4251</c2>
</quadruple>
<quadruple>
<d1>2501</d1>
<c1>3172</c1>
<d2>2563</d2>
<c2>1648</c2>
</quadruple>
<quadruple>
<d1>2563</d1>
<c1>4279</c1>
<d2>2623</d2>
<c2>3525</c2>
</quadruple>
<quadruple>
<d1>2623</d1>
<c1>2683</c1>
<d2>2696</d2>
<c2>3462</c2>
</quadruple>
<quadruple>
<d1>2696</d1>
<c1>698</c1>
<d2>2704</d2>
<c2>1623</c2>
</quadruple>
<quadruple>
<d1>2704</d1>
<c1>1247</c1>
<d2>2807</d2>
<c2>3047</c2>
</quadruple>
<quadruple>
<d1>2807</d1>
<c1>5262</c1>
<d2>2848</d2>
<c2>3677</c2>
</quadruple>
<quadruple>
<d1>2848</d1>
<c1>4071</c1>
<d2>2937</d2>
<c2>1481</c2>
</quadruple>
<quadruple>
<d1>2937</d1>
<c1>4646</c1>
<d2>2996</d2>
<c2>4449</c2>
</quadruple>
<quadruple>
<d1>2996</d1>
<c1>2412</c1>
<d2>3021</d2>
<c2>5516</c2>
</quadruple>
<quadruple>
<d1>3021</d1>
<c1>2318</c1>
<d2>6005</d2>
<c2>4967</c2>
</quadruple>
</right>
</node>
</tree>